{
    "review": [
        {
            "content": "Khoá học này thực sự rất chất lượng. Mình từ một người làm Sale, chưa biết gì về HTML, CSS, JS, mà giờ code được 1 web hoàn chỉnh. Mentor thì hỗ trợ nhiệt tình, lên lớp học lý thuyết xong là thực chiến luôn, về nhà thì livestream sửa bài, có khi tới 1-2h sáng luôn. Sau khoá học thì được các mentor chia sẻ kinh nghiệm.\n",
            "cover": "/img/tesimonials/tung-cfd.jpg",
            "date": "12/09/2020",
            "fb": "https://www.facebook.com/thanhtung.nguyen.5030927",
            "name": "Nguyễn Thanh Tùng"
        },
        {
            "content": "Mình đã từng tự học nhưng bị mất phương hướng trầm trọng, sau khóa học mình đã tự code được 2 dự án riêng, 4 mentor dạy và hỗ trợ học viên rất có tâm, chuyện livestream giải đáp thắc mắc cho học viên tới khuya là thường xuyên. Sau khóa học mình học được cách tạo giao diện sao cho đẹp tinh tế, thân thiện với người dùng.\n",
            "cover": "/img/tesimonials/van-tuan-cfd.jpg",
            "date": "10/10/2020",
            "fb": "https://www.facebook.com/profile.php?id=100015379562948",
            "name": "Nguyễn Anh Tuấn"
        },
        {
            "content": "Các mentor dạy có tâm, nhiệt tình. Mình là người chưa biết html và css, sau khóa học thì mình có thể tự tin code được giao diện theo thiết kế và cả việc xử lí các sự kiện bằng javascript và jquery.\n",
            "cover": "/img/tesimonials/thanh-trung-cfd.jpg",
            "date": "02/10/2020",
            "fb": "https://www.facebook.com/profile.php?id=100004115677006",
            "name": "Phạm Thành Trung"
        },
        {
            "content": "Khoá học bổ ích, dễ hiểu, đặc biệt là rất thực chiến. Các mentor hài hước, nhiều kinh nghiệm. Nói chung là ai không học thì uổng lắm =))))))))))\n",
            "cover": "/img/tesimonials/long-cfd.jpg",
            "date": "08/10/2020",
            "fb": "",
            "name": "Ngô Thành Long"
        },
        {
            "content": "Mình đã từng tự học nhưng bị mất phương hướng trầm trọng, sau khóa học mình đã tự code được 2 dự án riêng, 4 mentor dạy và hỗ trợ học viên rất có tâm, chuyện livestream giải đáp thắc mắc cho học viên tới khuya là thường xuyên. Sau khóa học mình học được cách tạo giao diện sao cho đẹp tinh tế, thân thiện với người dùng.\n",
            "cover": "/img/tesimonials/thanh-cfd.jpg",
            "date": "10/10/2020",
            "fb": "https://www.facebook.com/profile.php?id=100014103678202",
            "name": "Nguyễn Đình Thanh"
        },
        {
            "content": "Là một nơi truyền cảm hứng cho mình thực hiện tiếp ước mơ và hoài bảo! Cảm ơn các thầy đã nổ lực hỗ trợ để mình có thể tiếp cận ước mơ của mình gần hơn.\n",
            "cover": "/img/tesimonials/tuan-cfd-2.jpg",
            "date": "08/10/2020",
            "fb": "https://www.facebook.com/nat.theguardian/",
            "name": "Nguyễn Anh Tuấn"
        }
    ]
}